dytop/Bistable_RoA.py
dytop/CMGDB_util.py
dytop/Grid.py
dytop/Lips.py
dytop/Morse_graph_updated.py
dytop/MultivaluedMap.py
dytop/PlotRoA.py
dytop/Poset.py
dytop/RoA.py
dytop/__init__.py
dytop/dyn_tools.py
dytop-0.1.13.dist-info/LICENSE
dytop-0.1.13.dist-info/METADATA
dytop-0.1.13.dist-info/WHEEL
dytop-0.1.13.dist-info/top_level.txt
dytop-0.1.13.dist-info/RECORD
