Metadata-Version: 2.1
Name: dytop
Version: 0.1.13
Summary: dytop: combinatorial DYnamics and TOPology
Home-page: https://github.com/Ewerton-Vieira/dytop.git
Author: Ewerton Rocha Vieira
License-File: LICENSE
Requires-Dist: numpy
Requires-Dist: scipy
Requires-Dist: matplotlib
Requires-Dist: CMGDB
Requires-Dist: pychomp2
